Steganography/__init__.py
Steganography/steg.py
Steganography/test_steg.py
steganographyPy-0.0.2.dist-info/METADATA
steganographyPy-0.0.2.dist-info/WHEEL
steganographyPy-0.0.2.dist-info/top_level.txt
steganographyPy-0.0.2.dist-info/RECORD
