Metadata-Version: 2.1
Name: steganographyPy
Version: 0.0.2
Summary: Encodes text into image
Home-page: UNKNOWN
Author: Kryzma
Author-email: <gramolis1@gmail.com>
License: UNKNOWN
Keywords: python,steganography
Platform: UNKNOWN
Classifier: Development Status :: 1 - Planning
Classifier: Intended Audience :: Developers
Classifier: Programming Language :: Python :: 3
Classifier: Operating System :: Unix
Classifier: Operating System :: MacOS :: MacOS X
Classifier: Operating System :: Microsoft :: Windows
Requires-Dist: numpy
